{
  "applications": ["SkillContext"],
  "changelogDate": "20230518163031",
  "clientRootFolder": "SkillContext",
  "databaseType": "sql",
  "dto": "mapstruct",
  "embedded": false,
  "entityTableName": "category_id",
  "fields": [
    {
      "fieldName": "categoryId",
      "fieldType": "Long"
    }
  ],
  "fluentMethods": true,
  "jpaMetamodelFiltering": false,
  "microserviceName": "SkillContext",
  "name": "CategoryId",
  "pagination": "no",
  "readOnly": true,
  "relationships": [],
  "service": "serviceClass"
}
